[
    {
        "index": 0,
        "words": "-"
    },
    {
        "index": 1,
        "words": "батькиных"
    },
    {
        "index": 2,
        "words": "белорусский"
    },
    {
        "index": 3,
        "words": "боеспособный"
    },
    {
        "index": 4,
        "words": "взводный"
    },
    {
        "index": 5,
        "words": "военно"
    },
    {
        "index": 6,
        "words": "втемную"
    },
    {
        "index": 7,
        "words": "высокопоставленный"
    },
    {
        "index": 8,
        "words": "заметный"
    },
    {
        "index": 9,
        "words": "кадровый"
    },
    {
        "index": 10,
        "words": "картинный"
    },
    {
        "index": 11,
        "words": "командирский"
    },
    {
        "index": 12,
        "words": "краснодарский"
    },
    {
        "index": 13,
        "words": "кристаллический"
    },
    {
        "index": 14,
        "words": "луганский"
    },
    {
        "index": 15,
        "words": "могилёвский"
    },
    {
        "index": 16,
        "words": "мониторинговый"
    },
    {
        "index": 17,
        "words": "неудавшийся"
    },
    {
        "index": 18,
        "words": "неформальный"
    },
    {
        "index": 19,
        "words": "партизанский"
    },
    {
        "index": 20,
        "words": "петербургский"
    },
    {
        "index": 21,
        "words": "поддерживающий"
    },
    {
        "index": 22,
        "words": "привычный"
    },
    {
        "index": 23,
        "words": "пробитых"
    },
    {
        "index": 24,
        "words": "промежуточный"
    },
    {
        "index": 25,
        "words": "ротный"
    },
    {
        "index": 26,
        "words": "самопровозглашённый"
    },
    {
        "index": 27,
        "words": "сирийский"
    },
    {
        "index": 28,
        "words": "схваченные"
    },
    {
        "index": 29,
        "words": "авиабаза"
    },
    {
        "index": 30,
        "words": "базирование"
    },
    {
        "index": 31,
        "words": "баннер"
    },
    {
        "index": 32,
        "words": "блокпост"
    },
    {
        "index": 33,
        "words": "боеспособность"
    },
    {
        "index": 34,
        "words": "вагнеровцам"
    },
    {
        "index": 35,
        "words": "вагнеровцами"
    },
    {
        "index": 36,
        "words": "вагнеровцев"
    },
    {
        "index": 37,
        "words": "вагнеровцы"
    },
    {
        "index": 38,
        "words": "вербовка"
    },
    {
        "index": 39,
        "words": "военнослужащий"
    },
    {
        "index": 40,
        "words": "двумя"
    },
    {
        "index": 41,
        "words": "дислокация"
    },
    {
        "index": 42,
        "words": "европеец"
    },
    {
        "index": 43,
        "words": "закладки"
    },
    {
        "index": 44,
        "words": "импотенция"
    },
    {
        "index": 45,
        "words": "клоп"
    },
    {
        "index": 46,
        "words": "коврижка"
    },
    {
        "index": 47,
        "words": "менеджмент"
    },
    {
        "index": 48,
        "words": "методичка"
    },
    {
        "index": 49,
        "words": "переговорщик"
    },
    {
        "index": 50,
        "words": "передке"
    },
    {
        "index": 51,
        "words": "псевдогенералов"
    },
    {
        "index": 52,
        "words": "разведрота"
    },
    {
        "index": 53,
        "words": "реформирование"
    },
    {
        "index": 54,
        "words": "родным"
    },
    {
        "index": 55,
        "words": "силовик"
    },
    {
        "index": 56,
        "words": "сослуживец"
    },
    {
        "index": 57,
        "words": "спецслужба"
    },
    {
        "index": 58,
        "words": "телеграм"
    },
    {
        "index": 59,
        "words": "турбаза"
    },
    {
        "index": 60,
        "words": "уголовка"
    },
    {
        "index": 61,
        "words": "укрепрайоны"
    },
    {
        "index": 62,
        "words": "улики"
    },
    {
        "index": 63,
        "words": "формирование"
    },
    {
        "index": 64,
        "words": "формулировка"
    },
    {
        "index": 65,
        "words": "чекан"
    },
    {
        "index": 66,
        "words": "чекист"
    },
    {
        "index": 67,
        "words": "юг"
    },
    {
        "index": 68,
        "words": "авиамаршруты"
    },
    {
        "index": 69,
        "words": "вербовать"
    },
    {
        "index": 70,
        "words": "возвести"
    },
    {
        "index": 71,
        "words": "вынимать"
    },
    {
        "index": 72,
        "words": "держим"
    },
    {
        "index": 73,
        "words": "захлебнуться"
    },
    {
        "index": 74,
        "words": "исчислять"
    },
    {
        "index": 75,
        "words": "легитимизироваться"
    },
    {
        "index": 76,
        "words": "моемся"
    },
    {
        "index": 77,
        "words": "мочь"
    },
    {
        "index": 78,
        "words": "нет"
    },
    {
        "index": 79,
        "words": "обескуражить"
    },
    {
        "index": 80,
        "words": "обороняться"
    },
    {
        "index": 81,
        "words": "опергрупп"
    },
    {
        "index": 82,
        "words": "отсылать"
    },
    {
        "index": 83,
        "words": "перебросить"
    },
    {
        "index": 84,
        "words": "перекантоваться"
    },
    {
        "index": 85,
        "words": "подразумевали"
    },
    {
        "index": 86,
        "words": "последовавшие"
    },
    {
        "index": 87,
        "words": "преследоваться"
    },
    {
        "index": 88,
        "words": "просвистеть"
    },
    {
        "index": 89,
        "words": "простейшее"
    },
    {
        "index": 90,
        "words": "разломали"
    },
    {
        "index": 91,
        "words": "разуметься"
    },
    {
        "index": 92,
        "words": "сокрушаться"
    },
    {
        "index": 93,
        "words": "сплотиться"
    },
    {
        "index": 94,
        "words": "ставьте"
    },
    {
        "index": 95,
        "words": "схватиться"
    },
    {
        "index": 96,
        "words": "усугубить"
    },
    {
        "index": 97,
        "words": "чистимся"
    },
    {
        "index": 98,
        "words": "эмигрировать"
    }
]