[
    {
        "index": 0,
        "words": "бронзовый"
    },
    {
        "index": 1,
        "words": "высокопоставленный"
    },
    {
        "index": 2,
        "words": "сталинградская"
    },
    {
        "index": 3,
        "words": "сталинградской"
    },
    {
        "index": 4,
        "words": "-"
    },
    {
        "index": 5,
        "words": "закладки"
    },
    {
        "index": 6,
        "words": "панорама"
    },
    {
        "index": 7,
        "words": "репрессия"
    }
]