[
    {
        "index": 0,
        "words": "лояльный"
    },
    {
        "index": 1,
        "words": "показательный"
    },
    {
        "index": 2,
        "words": "понятийный"
    },
    {
        "index": 3,
        "words": "провоенные"
    },
    {
        "index": 4,
        "words": "-"
    },
    {
        "index": 5,
        "words": "ад"
    },
    {
        "index": 6,
        "words": "закладки"
    },
    {
        "index": 7,
        "words": "нелояльность"
    },
    {
        "index": 8,
        "words": "неприкасаемым"
    },
    {
        "index": 9,
        "words": "нестабильность"
    },
    {
        "index": 10,
        "words": "подкаст"
    },
    {
        "index": 11,
        "words": "политолог"
    },
    {
        "index": 12,
        "words": "путинизма"
    },
    {
        "index": 13,
        "words": "рассылка"
    },
    {
        "index": 14,
        "words": "репрессия"
    },
    {
        "index": 15,
        "words": "спецслужба"
    },
    {
        "index": 16,
        "words": "телеграм"
    },
    {
        "index": 17,
        "words": "тоталитаризм"
    },
    {
        "index": 18,
        "words": "трансформация"
    },
    {
        "index": 19,
        "words": "ютьюб"
    },
    {
        "index": 20,
        "words": "мочь"
    },
    {
        "index": 21,
        "words": "нет"
    },
    {
        "index": 22,
        "words": "подпишитесь"
    },
    {
        "index": 23,
        "words": "расценить"
    },
    {
        "index": 24,
        "words": "формировать"
    }
]